LICENSE
README.md
pyproject.toml
setup.cfg
setup.py
tests/__init__.py
tests/data/__init__.py
tests/test_wavematic/__init__.py
tests/test_wavematic/test_noise.py
tests/test_wavematic/test_timeaxis.py
wavematic/__init__.py
wavematic/wave.py
wavematic.egg-info/PKG-INFO
wavematic.egg-info/SOURCES.txt
wavematic.egg-info/dependency_links.txt
wavematic.egg-info/requires.txt
wavematic.egg-info/top_level.txt