Metadata-Version: 2.1
Name: wavematic
Version: 0.2.3
Summary: Simple wave generator
Home-page: https://github.com/MicaelJarniac/Wavematic
Author: Micael Jarniac
Author-email: micael@jarniac.dev
License: UNKNOWN
Project-URL: Bug Tracker, https://github.com/MicaelJarniac/Wavematic/issues
Platform: UNKNOWN
Classifier: Programming Language :: Python :: 3
Classifier: License :: OSI Approved :: MIT License
Classifier: Operating System :: OS Independent
Requires-Python: >=3.7
License-File: LICENSE
